repro/__init__.py
repro/__main__.py
repro/testing.py
repro/version.py
repro/commands/__init__.py
repro/commands/predict.py
repro/commands/pull.py
repro/commands/setup.py
repro/commands/subcommand.py
repro/commands/util.py
repro/common/__init__.py
repro/common/checks.py
repro/common/docker.py
repro/common/io.py
repro/common/logging.py
repro/common/registrable.py
repro/common/tempdir.py
repro/common/util.py
repro/data/__init__.py
repro/data/types.py
repro/data/dataset_readers/__init__.py
repro/data/dataset_readers/dataset_reader.py
repro/data/dataset_readers/datasets.py
repro/data/dataset_readers/jsonl.py
repro/data/dataset_readers/sacrerouge.py
repro/data/output_writers/__init__.py
repro/data/output_writers/default.py
repro/data/output_writers/metrics.py
repro/data/output_writers/output_writer.py
repro/data/output_writers/sacrerouge.py
repro/models/__init__.py
repro/models/model.py
repro/models/_models/Template.md
repro/models/_models/chen2020/Dockerfile
repro/models/_models/chen2020/Readme.md
repro/models/_models/chen2020/experiments/reproduce-results/Readme.md
repro/models/_models/chen2020/experiments/reproduce-results/run.sh
repro/models/_models/chen2020/scripts/warmup.sh
repro/models/_models/chen2020/src/__init__.py
repro/models/_models/chen2020/src/predict.py
repro/models/_models/chen2020/tests/__init__.py
repro/models/_models/chen2020/tests/models_test.py
repro/models/_models/chen2020/tests/fixtures/examples.json
repro/models/_models/colombo2021/Dockerfile
repro/models/_models/colombo2021/Readme.md
repro/models/_models/colombo2021/scripts/warmup.sh
repro/models/_models/colombo2021/src/score_cli.py
repro/models/_models/colombo2021/tests/__init__.py
repro/models/_models/colombo2021/tests/models_test.py
repro/models/_models/colombo2021/tests/fixtures/expected.json
repro/models/_models/colombo2021/tests/fixtures/hyps.txt
repro/models/_models/colombo2021/tests/fixtures/refs.txt
repro/models/_models/denkowski2014/Dockerfile
repro-0.1.6.dist-info/LICENSE
repro-0.1.6.dist-info/METADATA
repro-0.1.6.dist-info/WHEEL
repro-0.1.6.dist-info/entry_points.txt
repro-0.1.6.dist-info/top_level.txt
repro-0.1.6.dist-info/RECORD
