Metadata-Version: 2.1
Name: repro
Version: 0.1.6
Summary: An open-source library for reproducing results from research papers
Home-page: https://github.com/danieldeutsch/repro
Author: Daniel Deutsch
License: UNKNOWN
Platform: UNKNOWN
Requires-Python: >=3.6
License-File: LICENSE
Requires-Dist: datasets (>=1.2.1)
Requires-Dist: docker (==5.0.0)
Requires-Dist: joblib
Requires-Dist: overrides (==3.1.0)
Requires-Dist: pytest
Requires-Dist: six (==1.16.0)
